CHANGELOG.md
LICENSE.txt
MANIFEST.in
README.md
requirements.txt
setup.py
docs/expander-logo.svg
docs/expander-schematic.svg
expander/__init__.py
expander/api.py
expander/common.py
expander/correlator.py
expander/deduper.py
expander/poker.py
expander.egg-info/PKG-INFO
expander.egg-info/SOURCES.txt
expander.egg-info/dependency_links.txt
expander.egg-info/entry_points.txt
expander.egg-info/requires.txt
expander.egg-info/top_level.txt
expander/cache/__init__.py
expander/cache/responder.py
expander/peekaboo/__init__.py
expander/peekaboo/submitter.py
expander/peekaboo/tracker.py