Metadata-Version: 2.1
Name: expander
Version: 0.0.3
Summary: Karton-based archive extractor, job submitter and tracker as well as results correlator for use with Peekaboo
Home-page: https://github.com/science-computing/expander.git
Download-URL: https://github.com/science-computing/expander/archive/master.zip
Author: Michael Weiser
Author-email: michael.weiser@gmx.de
License: GPLv3
Keywords: Karton,Peekaboo,rspamd
Classifier: Development Status :: 4 - Beta
Classifier: Operating System :: POSIX
Classifier: Programming Language :: Python
Classifier: Programming Language :: Python :: 3
Classifier: License :: OSI Approved :: GNU General Public License v3 (GPLv3)
Classifier: Natural Language :: English
Classifier: Natural Language :: German
Classifier: Topic :: Communications :: Email :: Filters
Requires-Python: >=3.8
License-File: LICENSE.txt
